<?xml version="1.0" encoding="utf-8" ?>
<dwsync>
<file name="5star.png" server="webdev.testsp.com//Inetpub/webdev/" local="130780082925547442" remote="130773944400000000" Dst="2" />
<file name="aec.png" server="webdev.testsp.com//Inetpub/webdev/" local="130780082924527340" remote="130773944400000000" Dst="2" />
<file name="americanhealth.png" server="webdev.testsp.com//Inetpub/webdev/" local="130780082924837371" remote="130773944400000000" Dst="2" />
<file name="amerifund.png" server="webdev.testsp.com//Inetpub/webdev/" local="130780082925137401" remote="130773944400000000" Dst="2" />
<file name="assistedliving.png" server="webdev.testsp.com//Inetpub/webdev/" local="130780082927217609" remote="130773944400000000" Dst="2" />
<file name="bettybrigade.png" server="webdev.testsp.com//Inetpub/webdev/" local="130780082925437431" remote="130773944400000000" Dst="2" />
<file name="buelow.png" server="webdev.testsp.com//Inetpub/webdev/" local="130780082927887676" remote="130773944400000000" Dst="2" />
<file name="cassidyturley.png" server="webdev.testsp.com//Inetpub/webdev/" local="130780082927937681" remote="130773944400000000" Dst="2" />
<file name="cdi.png" server="webdev.testsp.com//Inetpub/webdev/" local="130780082928227710" remote="130773944400000000" Dst="2" />
<file name="chartercapital.png" server="webdev.testsp.com//Inetpub/webdev/" local="130780082928247712" remote="130773944400000000" Dst="2" />
<file name="designnorth.png" server="webdev.testsp.com//Inetpub/webdev/" local="130780082928437731" remote="130773944400000000" Dst="2" />
<file name="fiestabowl.png" server="webdev.testsp.com//Inetpub/webdev/" local="130780082930527940" remote="130773944400000000" Dst="2" />
<file name="hawaiirealestate.png" server="webdev.testsp.com//Inetpub/webdev/" local="130780082928637751" remote="130773944400000000" Dst="2" />
<file name="healthcarepartners.png" server="webdev.testsp.com//Inetpub/webdev/" local="130780082928777765" remote="130773944400000000" Dst="2" />
<file name="jdagroup.png" server="webdev.testsp.com//Inetpub/webdev/" local="130780082931037991" remote="130773944400000000" Dst="2" />
<file name="keevac.png" server="webdev.testsp.com//Inetpub/webdev/" local="130780082931077995" remote="130773944400000000" Dst="2" />
<file name="kmmedical.png" server="webdev.testsp.com//Inetpub/webdev/" local="130780082931408028" remote="130773944400000000" Dst="2" />
<file name="mtncitymeat.png" server="webdev.testsp.com//Inetpub/webdev/" local="130780082933678255" remote="130773944400000000" Dst="2" />
<file name="pdm.png" server="webdev.testsp.com//Inetpub/webdev/" local="130780082931468034" remote="130773944400000000" Dst="2" />
<file name="recordedbooks.png" server="webdev.testsp.com//Inetpub/webdev/" local="130780082931768064" remote="130773944400000000" Dst="2" />
<file name="sandlertraining.png" server="webdev.testsp.com//Inetpub/webdev/" local="130780082931968084" remote="130773944400000000" Dst="2" />
<file name="superior.png" server="webdev.testsp.com//Inetpub/webdev/" local="130780082932098097" remote="130773944400000000" Dst="2" />
<file name="tc.png" server="webdev.testsp.com//Inetpub/webdev/" local="130780082932248112" remote="130773944400000000" Dst="2" />
<file name="turnock.png" server="webdev.testsp.com//Inetpub/webdev/" local="130780082934308318" remote="130773944400000000" Dst="2" />
<file name="zaxis.png" server="webdev.testsp.com//Inetpub/webdev/" local="130780082932568144" remote="130773944400000000" Dst="2" />
<file name="zyvax.png" server="webdev.testsp.com//Inetpub/webdev/" local="130780082935948482" remote="130773944400000000" Dst="2" />
<file name="5star.png" server="webdev.testsp.com/Inetpub/webdeva/" local="130549303882785732" remote="130728049800000000" Dst="2" />
<file name="aec.png" server="webdev.testsp.com/Inetpub/webdeva/" local="130549303882805734" remote="130728049800000000" Dst="2" />
<file name="americanhealth.png" server="webdev.testsp.com/Inetpub/webdeva/" local="130549303882825736" remote="130728049800000000" Dst="2" />
<file name="amerifund.png" server="webdev.testsp.com/Inetpub/webdeva/" local="130549303882835737" remote="130728049800000000" Dst="2" />
<file name="assistedliving.png" server="webdev.testsp.com/Inetpub/webdeva/" local="130549303883195773" remote="130728049800000000" Dst="2" />
<file name="bettybrigade.png" server="webdev.testsp.com/Inetpub/webdeva/" local="130549303883245778" remote="130728049800000000" Dst="2" />
<file name="buelow.png" server="webdev.testsp.com/Inetpub/webdeva/" local="130549303883295783" remote="130728049800000000" Dst="2" />
<file name="cassidyturley.png" server="webdev.testsp.com/Inetpub/webdeva/" local="130549303883345788" remote="130728049800000000" Dst="2" />
<file name="cdi.png" server="webdev.testsp.com/Inetpub/webdeva/" local="130549303883385792" remote="130728049800000000" Dst="2" />
<file name="chartercapital.png" server="webdev.testsp.com/Inetpub/webdeva/" local="130549303883435797" remote="130728049800000000" Dst="2" />
<file name="designnorth.png" server="webdev.testsp.com/Inetpub/webdeva/" local="130549303883465800" remote="130728049800000000" Dst="2" />
<file name="fiestabowl.png" server="webdev.testsp.com/Inetpub/webdeva/" local="130549303883485802" remote="130728049800000000" Dst="2" />
<file name="hawaiirealestate.png" server="webdev.testsp.com/Inetpub/webdeva/" local="130549303883515805" remote="130728049800000000" Dst="2" />
<file name="healthcarepartners.png" server="webdev.testsp.com/Inetpub/webdeva/" local="130549303883535807" remote="130728049800000000" Dst="2" />
<file name="jdagroup.png" server="webdev.testsp.com/Inetpub/webdeva/" local="130549303883555809" remote="130728049800000000" Dst="2" />
<file name="keevac.png" server="webdev.testsp.com/Inetpub/webdeva/" local="130549303883585812" remote="130728049800000000" Dst="2" />
<file name="kmmedical.png" server="webdev.testsp.com/Inetpub/webdeva/" local="130549303883605814" remote="130728049800000000" Dst="2" />
<file name="mtncitymeat.png" server="webdev.testsp.com/Inetpub/webdeva/" local="130549303883635817" remote="130728049800000000" Dst="2" />
<file name="pdm.png" server="webdev.testsp.com/Inetpub/webdeva/" local="130549303883655819" remote="130728049800000000" Dst="2" />
<file name="recordedbooks.png" server="webdev.testsp.com/Inetpub/webdeva/" local="130549303883685822" remote="130728049800000000" Dst="2" />
<file name="sandlertraining.png" server="webdev.testsp.com/Inetpub/webdeva/" local="130549303883705824" remote="130728049800000000" Dst="2" />
<file name="superior.png" server="webdev.testsp.com/Inetpub/webdeva/" local="130549303883815835" remote="130728049800000000" Dst="2" />
<file name="tc.png" server="webdev.testsp.com/Inetpub/webdeva/" local="130549303883845838" remote="130728049800000000" Dst="2" />
<file name="zaxis.png" server="webdev.testsp.com/Inetpub/webdeva/" local="130549303883885842" remote="130728049800000000" Dst="2" />
<file name="zyvax.png" server="webdev.testsp.com/Inetpub/webdeva/" local="130549303883915845" remote="130728049800000000" Dst="2" />
<file name="turnock.png" server="webdev.testsp.com/Inetpub/webdeva/" local="130549303883865840" remote="130728049800000000" Dst="2" />
<file name="5star.png" server="webdev.testsp.com/Inetpub/webdev/" local="130549303882785732" remote="130752545400000000" Dst="2" />
<file name="aec.png" server="webdev.testsp.com/Inetpub/webdev/" local="130549303882805734" remote="130752545400000000" Dst="2" />
<file name="americanhealth.png" server="webdev.testsp.com/Inetpub/webdev/" local="130549303882825736" remote="130752545400000000" Dst="2" />
<file name="amerifund.png" server="webdev.testsp.com/Inetpub/webdev/" local="130549303882835737" remote="130752545400000000" Dst="2" />
<file name="assistedliving.png" server="webdev.testsp.com/Inetpub/webdev/" local="130549303883195773" remote="130752545400000000" Dst="2" />
<file name="bettybrigade.png" server="webdev.testsp.com/Inetpub/webdev/" local="130549303883245778" remote="130752545400000000" Dst="2" />
<file name="buelow.png" server="webdev.testsp.com/Inetpub/webdev/" local="130549303883295783" remote="130752545400000000" Dst="2" />
<file name="cassidyturley.png" server="webdev.testsp.com/Inetpub/webdev/" local="130549303883345788" remote="130752545400000000" Dst="2" />
<file name="cdi.png" server="webdev.testsp.com/Inetpub/webdev/" local="130549303883385792" remote="130752545400000000" Dst="2" />
<file name="chartercapital.png" server="webdev.testsp.com/Inetpub/webdev/" local="130549303883435797" remote="130752545400000000" Dst="2" />
<file name="designnorth.png" server="webdev.testsp.com/Inetpub/webdev/" local="130549303883465800" remote="130752545400000000" Dst="2" />
<file name="fiestabowl.png" server="webdev.testsp.com/Inetpub/webdev/" local="130549303883485802" remote="130752545400000000" Dst="2" />
<file name="hawaiirealestate.png" server="webdev.testsp.com/Inetpub/webdev/" local="130549303883515805" remote="130752545400000000" Dst="2" />
<file name="healthcarepartners.png" server="webdev.testsp.com/Inetpub/webdev/" local="130549303883535807" remote="130752545400000000" Dst="2" />
<file name="jdagroup.png" server="webdev.testsp.com/Inetpub/webdev/" local="130549303883555809" remote="130752545400000000" Dst="2" />
<file name="keevac.png" server="webdev.testsp.com/Inetpub/webdev/" local="130549303883585812" remote="130752545400000000" Dst="2" />
<file name="kmmedical.png" server="webdev.testsp.com/Inetpub/webdev/" local="130549303883605814" remote="130752545400000000" Dst="2" />
<file name="mtncitymeat.png" server="webdev.testsp.com/Inetpub/webdev/" local="130549303883635817" remote="130752545400000000" Dst="2" />
<file name="pdm.png" server="webdev.testsp.com/Inetpub/webdev/" local="130549303883655819" remote="130752545400000000" Dst="2" />
<file name="recordedbooks.png" server="webdev.testsp.com/Inetpub/webdev/" local="130549303883685822" remote="130752545400000000" Dst="2" />
<file name="sandlertraining.png" server="webdev.testsp.com/Inetpub/webdev/" local="130549303883705824" remote="130752545400000000" Dst="2" />
<file name="superior.png" server="webdev.testsp.com/Inetpub/webdev/" local="130549303883815835" remote="130752545400000000" Dst="2" />
<file name="tc.png" server="webdev.testsp.com/Inetpub/webdev/" local="130549303883845838" remote="130752545400000000" Dst="2" />
<file name="turnock.png" server="webdev.testsp.com/Inetpub/webdev/" local="130549303883865840" remote="130752545400000000" Dst="2" />
<file name="zaxis.png" server="webdev.testsp.com/Inetpub/webdev/" local="130549303883885842" remote="130752545400000000" Dst="2" />
<file name="zyvax.png" server="webdev.testsp.com/Inetpub/webdev/" local="130549303883915845" remote="130752545400000000" Dst="2" />
<file name="5star.png" server="216.241.183.40//Inetpub/act_com/" local="130780082925547442" remote="130780086600000000" Dst="2" />
<file name="aec.png" server="216.241.183.40//Inetpub/act_com/" local="130780082924527340" remote="130780086600000000" Dst="2" />
<file name="americanhealth.png" server="216.241.183.40//Inetpub/act_com/" local="130780082924837371" remote="130780086600000000" Dst="2" />
<file name="amerifund.png" server="216.241.183.40//Inetpub/act_com/" local="130780082925137401" remote="130780086600000000" Dst="2" />
<file name="assistedliving.png" server="216.241.183.40//Inetpub/act_com/" local="130780082927217609" remote="130780086600000000" Dst="2" />
<file name="bettybrigade.png" server="216.241.183.40//Inetpub/act_com/" local="130780082925437431" remote="130780086600000000" Dst="2" />
<file name="buelow.png" server="216.241.183.40//Inetpub/act_com/" local="130780082927887676" remote="130780086600000000" Dst="2" />
<file name="cassidyturley.png" server="216.241.183.40//Inetpub/act_com/" local="130780082927937681" remote="130780086600000000" Dst="2" />
<file name="cdi.png" server="216.241.183.40//Inetpub/act_com/" local="130780082928227710" remote="130780086600000000" Dst="2" />
<file name="chartercapital.png" server="216.241.183.40//Inetpub/act_com/" local="130780082928247712" remote="130780086600000000" Dst="2" />
<file name="designnorth.png" server="216.241.183.40//Inetpub/act_com/" local="130780082928437731" remote="130780086600000000" Dst="2" />
<file name="fiestabowl.png" server="216.241.183.40//Inetpub/act_com/" local="130780082930527940" remote="130780086600000000" Dst="2" />
<file name="hawaiirealestate.png" server="216.241.183.40//Inetpub/act_com/" local="130780082928637751" remote="130780086600000000" Dst="2" />
<file name="healthcarepartners.png" server="216.241.183.40//Inetpub/act_com/" local="130780082928777765" remote="130780086600000000" Dst="2" />
<file name="jdagroup.png" server="216.241.183.40//Inetpub/act_com/" local="130780082931037991" remote="130780086600000000" Dst="2" />
<file name="keevac.png" server="216.241.183.40//Inetpub/act_com/" local="130780082931077995" remote="130780086600000000" Dst="2" />
<file name="kmmedical.png" server="216.241.183.40//Inetpub/act_com/" local="130780082931408028" remote="130780086600000000" Dst="2" />
<file name="mtncitymeat.png" server="216.241.183.40//Inetpub/act_com/" local="130780082933678255" remote="130780086600000000" Dst="2" />
<file name="pdm.png" server="216.241.183.40//Inetpub/act_com/" local="130780082931468034" remote="130780086600000000" Dst="2" />
<file name="recordedbooks.png" server="216.241.183.40//Inetpub/act_com/" local="130780082931768064" remote="130780086600000000" Dst="2" />
<file name="sandlertraining.png" server="216.241.183.40//Inetpub/act_com/" local="130780082931968084" remote="130780086600000000" Dst="2" />
<file name="superior.png" server="216.241.183.40//Inetpub/act_com/" local="130780082932098097" remote="130780086600000000" Dst="2" />
<file name="tc.png" server="216.241.183.40//Inetpub/act_com/" local="130780082932248112" remote="130780086600000000" Dst="2" />
<file name="turnock.png" server="216.241.183.40//Inetpub/act_com/" local="130780082934308318" remote="130780086600000000" Dst="2" />
<file name="zaxis.png" server="216.241.183.40//Inetpub/act_com/" local="130780082932568144" remote="130780086600000000" Dst="2" />
<file name="zyvax.png" server="216.241.183.40//Inetpub/act_com/" local="130780082935948482" remote="130780086600000000" Dst="2" />
<file name="5star.png" server="webdev.testsp.com//Inetpub/webdevb/" local="130964070086362079" remote="130748036400000000" Dst="1" />
<file name="aec.png" server="webdev.testsp.com//Inetpub/webdevb/" local="130964070086512094" remote="130748036400000000" Dst="1" />
<file name="americanhealth.png" server="webdev.testsp.com//Inetpub/webdevb/" local="130964070086662109" remote="130748036400000000" Dst="1" />
<file name="amerifund.png" server="webdev.testsp.com//Inetpub/webdevb/" local="130964070086812124" remote="130748036400000000" Dst="1" />
<file name="bettybrigade.png" server="webdev.testsp.com//Inetpub/webdevb/" local="130964070087082151" remote="130748036400000000" Dst="1" />
<file name="chartercapital.png" server="webdev.testsp.com//Inetpub/webdevb/" local="130964070087402183" remote="130748036400000000" Dst="1" />
<file name="designnorth.png" server="webdev.testsp.com//Inetpub/webdevb/" local="130964070087422185" remote="130748036400000000" Dst="1" />
<file name="hawaiirealestate.png" server="webdev.testsp.com//Inetpub/webdevb/" local="130964070087822225" remote="130748036400000000" Dst="1" />
<file name="healthcarepartners.png" server="webdev.testsp.com//Inetpub/webdevb/" local="130964070087832226" remote="130748036400000000" Dst="1" />
<file name="keevac.png" server="webdev.testsp.com//Inetpub/webdevb/" local="130964070088172260" remote="130748036400000000" Dst="1" />
<file name="kmmedical.png" server="webdev.testsp.com//Inetpub/webdevb/" local="130964070088262269" remote="130748036400000000" Dst="1" />
<file name="mtncitymeat.png" server="webdev.testsp.com//Inetpub/webdevb/" local="130964070088572300" remote="130748036400000000" Dst="1" />
<file name="pdm.png" server="webdev.testsp.com//Inetpub/webdevb/" local="130964070088692312" remote="130748036400000000" Dst="1" />
<file name="buelow.png" server="webdev.testsp.com//Inetpub/webdevb/" local="130964070089092352" remote="130748036400000000" Dst="1" />
<file name="assistedliving.png" server="webdev.testsp.com//Inetpub/webdevb/" local="130964070089372380" remote="130748036400000000" Dst="1" />
<file name="cassidyturley.png" server="webdev.testsp.com//Inetpub/webdevb/" local="130964070089382381" remote="130748036400000000" Dst="1" />
<file name="cdi.png" server="webdev.testsp.com//Inetpub/webdevb/" local="130964070089382381" remote="130748036400000000" Dst="1" />
<file name="recordedbooks.png" server="webdev.testsp.com//Inetpub/webdevb/" local="130964070089392382" remote="130748036400000000" Dst="1" />
<file name="sandlertraining.png" server="webdev.testsp.com//Inetpub/webdevb/" local="130964070089922435" remote="130748036400000000" Dst="1" />
<file name="superior.png" server="webdev.testsp.com//Inetpub/webdevb/" local="130964070089942437" remote="130748036400000000" Dst="1" />
<file name="jdagroup.png" server="webdev.testsp.com//Inetpub/webdevb/" local="130964070089952438" remote="130748036400000000" Dst="1" />
<file name="tc.png" server="webdev.testsp.com//Inetpub/webdevb/" local="130964070089972440" remote="130748036400000000" Dst="1" />
<file name="zaxis.png" server="webdev.testsp.com//Inetpub/webdevb/" local="130964070089972440" remote="130748036400000000" Dst="1" />
<file name="fiestabowl.png" server="webdev.testsp.com//Inetpub/webdevb/" local="130964070090702513" remote="130748036400000000" Dst="1" />
<file name="zyvax.png" server="webdev.testsp.com//Inetpub/webdevb/" local="130964070090712514" remote="130748036400000000" Dst="1" />
<file name="turnock.png" server="webdev.testsp.com//Inetpub/webdevb/" local="130964070092312674" remote="130748036400000000" Dst="1" />
</dwsync>