<?xml version="1.0" encoding="utf-8" ?>
<dwsync>
<file name="real-estate.html" server="webdev.testsp.com//Inetpub/webdevd/" local="130673730156989393" remote="130673731200000000" Dst="1" />
<file name="financial-services.html" server="webdev.testsp.com//Inetpub/webdevd/" local="130673731004489729" remote="130673731200000000" Dst="1" />
<file name="topten-list.html" server="webdev.testsp.com//Inetpub/webdevd/" local="130673700278560410" remote="130673700600000000" Dst="1" />
<file name="construction.html" server="webdev.testsp.com//Inetpub/webdevd/" local="130673731215360269" remote="130673731200000000" Dst="1" />
<file name="government.html" server="webdev.testsp.com//Inetpub/webdevd/" local="130673730894638177" remote="130673731200000000" Dst="1" />
<file name="manufacturing.html" server="webdev.testsp.com//Inetpub/webdevd/" local="130673730712270241" remote="130673731200000000" Dst="1" />
<file name="education.html" server="webdev.testsp.com//Inetpub/webdevd/" local="130673731083652109" remote="130673731200000000" Dst="1" />
<file name="healthcare.html" server="webdev.testsp.com//Inetpub/webdevd/" local="130673730812628449" remote="130673731200000000" Dst="1" />
<file name="non-profit.html" server="webdev.testsp.com//Inetpub/webdevd/" local="130673730620069129" remote="130673731200000000" Dst="1" />
<file name="retail.html" server="webdev.testsp.com//Inetpub/webdevd/" local="130673729011076957" remote="130673731200000000" Dst="1" />
<file name="technology.html" server="webdev.testsp.com//Inetpub/webdevd/" local="130673728665257969" remote="130673731200000000" Dst="1" />
<file name="construction.html" server="216.241.183.40//Inetpub/act_com/" local="130673731215360269" remote="130753017000000000" Dst="2" />
<file name="education.html" server="216.241.183.40//Inetpub/act_com/" local="130673731083652109" remote="130753017000000000" Dst="2" />
<file name="financial-services.html" server="216.241.183.40//Inetpub/act_com/" local="130673731004489729" remote="130753017000000000" Dst="2" />
<file name="government.html" server="216.241.183.40//Inetpub/act_com/" local="130673730894638177" remote="130753017000000000" Dst="2" />
<file name="healthcare.html" server="216.241.183.40//Inetpub/act_com/" local="130673730812628449" remote="130753017000000000" Dst="2" />
<file name="manufacturing.html" server="216.241.183.40//Inetpub/act_com/" local="130673730712270241" remote="130753017000000000" Dst="2" />
<file name="non-profit.html" server="216.241.183.40//Inetpub/act_com/" local="130673730620069129" remote="130753017000000000" Dst="2" />
<file name="real-estate.html" server="216.241.183.40//Inetpub/act_com/" local="130673730156989393" remote="130753017000000000" Dst="2" />
<file name="retail.html" server="216.241.183.40//Inetpub/act_com/" local="130673729011076957" remote="130753017000000000" Dst="2" />
<file name="technology.html" server="216.241.183.40//Inetpub/act_com/" local="130673728665257969" remote="130753017000000000" Dst="2" />
<file name="topten-list.html" server="216.241.183.40//Inetpub/act_com/" local="130673700278560410" remote="130753017000000000" Dst="2" />
<file name="construction.html" server="webdev.testsp.com/Inetpub/webdeva/" local="130673731215360269" remote="130728046800000000" Dst="2" />
<file name="education.html" server="webdev.testsp.com/Inetpub/webdeva/" local="130673731083652109" remote="130728046800000000" Dst="2" />
<file name="financial-services.html" server="webdev.testsp.com/Inetpub/webdeva/" local="130673731004489729" remote="130728046800000000" Dst="2" />
<file name="government.html" server="webdev.testsp.com/Inetpub/webdeva/" local="130673730894638177" remote="130728046800000000" Dst="2" />
<file name="healthcare.html" server="webdev.testsp.com/Inetpub/webdeva/" local="130673730812628449" remote="130728046800000000" Dst="2" />
<file name="manufacturing.html" server="webdev.testsp.com/Inetpub/webdeva/" local="130673730712270241" remote="130728046800000000" Dst="2" />
<file name="non-profit.html" server="webdev.testsp.com/Inetpub/webdeva/" local="130673730620069129" remote="130728046800000000" Dst="2" />
<file name="real-estate.html" server="webdev.testsp.com/Inetpub/webdeva/" local="130673730156989393" remote="130728046800000000" Dst="2" />
<file name="retail.html" server="webdev.testsp.com/Inetpub/webdeva/" local="130673729011076957" remote="130728046800000000" Dst="2" />
<file name="technology.html" server="webdev.testsp.com/Inetpub/webdeva/" local="130673728665257969" remote="130728046800000000" Dst="2" />
<file name="topten-list.html" server="webdev.testsp.com/Inetpub/webdeva/" local="130673700278560410" remote="130728046800000000" Dst="2" />
<file name="construction.html" server="webdev.testsp.com/Inetpub/webdev/" local="130673731215360269" remote="130752541800000000" Dst="2" />
<file name="education.html" server="webdev.testsp.com/Inetpub/webdev/" local="130673731083652109" remote="130752541800000000" Dst="2" />
<file name="financial-services.html" server="webdev.testsp.com/Inetpub/webdev/" local="130673731004489729" remote="130752541800000000" Dst="2" />
<file name="government.html" server="webdev.testsp.com/Inetpub/webdev/" local="130673730894638177" remote="130752541800000000" Dst="2" />
<file name="healthcare.html" server="webdev.testsp.com/Inetpub/webdev/" local="130673730812628449" remote="130752541800000000" Dst="2" />
<file name="manufacturing.html" server="webdev.testsp.com/Inetpub/webdev/" local="130673730712270241" remote="130752541800000000" Dst="2" />
<file name="non-profit.html" server="webdev.testsp.com/Inetpub/webdev/" local="130673730620069129" remote="130752541800000000" Dst="2" />
<file name="real-estate.html" server="webdev.testsp.com/Inetpub/webdev/" local="130673730156989393" remote="130752541800000000" Dst="2" />
<file name="retail.html" server="webdev.testsp.com/Inetpub/webdev/" local="130673729011076957" remote="130752541800000000" Dst="2" />
<file name="technology.html" server="webdev.testsp.com/Inetpub/webdev/" local="130673728665257969" remote="130752541800000000" Dst="2" />
<file name="topten-list.html" server="webdev.testsp.com/Inetpub/webdev/" local="130673700278560410" remote="130752541800000000" Dst="2" />
<file name="construction.html" server="webdev.testsp.com//Inetpub/webdev/" local="130673731215360269" remote="130754094000000000" Dst="2" />
<file name="education.html" server="webdev.testsp.com//Inetpub/webdev/" local="130673731083652109" remote="130754094000000000" Dst="2" />
<file name="financial-services.html" server="webdev.testsp.com//Inetpub/webdev/" local="130673731004489729" remote="130754094000000000" Dst="2" />
<file name="government.html" server="webdev.testsp.com//Inetpub/webdev/" local="130673730894638177" remote="130754094000000000" Dst="2" />
<file name="healthcare.html" server="webdev.testsp.com//Inetpub/webdev/" local="130673730812628449" remote="130754094000000000" Dst="2" />
<file name="manufacturing.html" server="webdev.testsp.com//Inetpub/webdev/" local="130673730712270241" remote="130754094000000000" Dst="2" />
<file name="non-profit.html" server="webdev.testsp.com//Inetpub/webdev/" local="130673730620069129" remote="130754094000000000" Dst="2" />
<file name="real-estate.html" server="webdev.testsp.com//Inetpub/webdev/" local="130673730156989393" remote="130754094000000000" Dst="2" />
<file name="retail.html" server="webdev.testsp.com//Inetpub/webdev/" local="130673729011076957" remote="130754094000000000" Dst="2" />
<file name="technology.html" server="webdev.testsp.com//Inetpub/webdev/" local="130673728665257969" remote="130754094000000000" Dst="2" />
<file name="topten-list.html" server="webdev.testsp.com//Inetpub/webdev/" local="130673700278560410" remote="130754094000000000" Dst="2" />
</dwsync>