<?xml version="1.0" encoding="utf-8" ?>
<dwsync>
<file name="marketplace_v1b_front.png" server="webdev.testsp.com//Inetpub/webdevb/" local="130723158278923152" remote="130718790600000000" Dst="2" />
<file name="marketplace_v1c_front.png" server="webdev.testsp.com//Inetpub/webdevb/" local="130723158279153175" remote="130718790600000000" Dst="2" />
<file name="marketplace_v1d_back.png" server="webdev.testsp.com//Inetpub/webdevb/" local="130723158280153275" remote="130718790600000000" Dst="2" />
<file name="marketplace_v1d_front.png" server="webdev.testsp.com//Inetpub/webdevb/" local="130723158280323292" remote="130718790600000000" Dst="2" />
<file name="marketplace_v1b_back.png" server="webdev.testsp.com//Inetpub/webdevb/" local="130723158280473307" remote="130718790600000000" Dst="2" />
<file name="marketplace_v1_back.png" server="webdev.testsp.com//Inetpub/webdevb/" local="130723158281243384" remote="130718790600000000" Dst="2" />
<file name="marketplace_v1_front.png" server="webdev.testsp.com//Inetpub/webdevb/" local="130723158281263386" remote="130718790600000000" Dst="2" />
<file name="marketplace_v1b_back.png" server="webdev.testsp.com/Inetpub/webdeva/" local="130723158280473307" remote="130728046800000000" Dst="2" />
<file name="marketplace_v1b_front.png" server="webdev.testsp.com/Inetpub/webdeva/" local="130723158278923152" remote="130728046800000000" Dst="2" />
<file name="marketplace_v1c_front.png" server="webdev.testsp.com/Inetpub/webdeva/" local="130723158279153175" remote="130728046800000000" Dst="2" />
<file name="marketplace_v1d_back.png" server="webdev.testsp.com/Inetpub/webdeva/" local="130723158280153275" remote="130728046800000000" Dst="2" />
<file name="marketplace_v1d_front.png" server="webdev.testsp.com/Inetpub/webdeva/" local="130723158280323292" remote="130728046800000000" Dst="2" />
<file name="marketplace_v1_back.png" server="webdev.testsp.com/Inetpub/webdeva/" local="130723158281243384" remote="130728046800000000" Dst="2" />
<file name="marketplace_v1_front.png" server="webdev.testsp.com/Inetpub/webdeva/" local="130723158281263386" remote="130728046800000000" Dst="2" />
<file name="marketplace_v1b_back.png" server="webdev.testsp.com/Inetpub/webdev/" local="130723158280473307" remote="130752541800000000" Dst="2" />
<file name="marketplace_v1b_front.png" server="webdev.testsp.com/Inetpub/webdev/" local="130723158278923152" remote="130752541800000000" Dst="2" />
<file name="marketplace_v1c_front.png" server="webdev.testsp.com/Inetpub/webdev/" local="130723158279153175" remote="130752541800000000" Dst="2" />
<file name="marketplace_v1d_back.png" server="webdev.testsp.com/Inetpub/webdev/" local="130723158280153275" remote="130752541800000000" Dst="2" />
<file name="marketplace_v1d_front.png" server="webdev.testsp.com/Inetpub/webdev/" local="130723158280323292" remote="130752541800000000" Dst="2" />
<file name="marketplace_v1_back.png" server="webdev.testsp.com/Inetpub/webdev/" local="130723158281243384" remote="130752541800000000" Dst="2" />
<file name="marketplace_v1_front.png" server="webdev.testsp.com/Inetpub/webdev/" local="130723158281263386" remote="130752541800000000" Dst="2" />
<file name="marketplace_v1b_back.png" server="216.241.183.40//Inetpub/act_com/" local="130723158280473307" remote="130753017000000000" Dst="2" />
<file name="marketplace_v1b_front.png" server="216.241.183.40//Inetpub/act_com/" local="130723158278923152" remote="130753017000000000" Dst="2" />
<file name="marketplace_v1c_front.png" server="216.241.183.40//Inetpub/act_com/" local="130723158279153175" remote="130753017000000000" Dst="2" />
<file name="marketplace_v1d_back.png" server="216.241.183.40//Inetpub/act_com/" local="130723158280153275" remote="130753017000000000" Dst="2" />
<file name="marketplace_v1d_front.png" server="216.241.183.40//Inetpub/act_com/" local="130723158280323292" remote="130753017000000000" Dst="2" />
<file name="marketplace_v1_back.png" server="216.241.183.40//Inetpub/act_com/" local="130723158281243384" remote="130753017000000000" Dst="2" />
<file name="marketplace_v1_front.png" server="216.241.183.40//Inetpub/act_com/" local="130723158281263386" remote="130753017000000000" Dst="2" />
<file name="marketplace_v1b_back.png" server="webdev.testsp.com//Inetpub/webdev/" local="130723158280473307" remote="130754093400000000" Dst="2" />
<file name="marketplace_v1b_front.png" server="webdev.testsp.com//Inetpub/webdev/" local="130723158278923152" remote="130754093400000000" Dst="2" />
<file name="marketplace_v1c_front.png" server="webdev.testsp.com//Inetpub/webdev/" local="130723158279153175" remote="130754093400000000" Dst="2" />
<file name="marketplace_v1d_back.png" server="webdev.testsp.com//Inetpub/webdev/" local="130723158280153275" remote="130754093400000000" Dst="2" />
<file name="marketplace_v1d_front.png" server="webdev.testsp.com//Inetpub/webdev/" local="130723158280323292" remote="130754093400000000" Dst="2" />
<file name="marketplace_v1_back.png" server="webdev.testsp.com//Inetpub/webdev/" local="130723158281243384" remote="130754093400000000" Dst="2" />
<file name="marketplace_v1_front.png" server="webdev.testsp.com//Inetpub/webdev/" local="130723158281263386" remote="130754093400000000" Dst="2" />
</dwsync>